collective.preventactions-0.2.1-py2.7-nspkg.pth
collective/preventactions/__init__.py
collective/preventactions/configure.zcml
collective/preventactions/interfaces.py
collective/preventactions/prevent.py
collective/preventactions/setuphandlers.py
collective/preventactions/testing.py
collective/preventactions/testing.zcml
collective/preventactions/browser/__init__.py
collective/preventactions/browser/configure.zcml
collective/preventactions/browser/preventactions.py
collective/preventactions/browser/views.py
collective/preventactions/browser/static/.gitkeep
collective/preventactions/locales/collective.preventdelete.pot
collective/preventactions/profiles/default/actions.xml
collective/preventactions/profiles/default/browserlayer.xml
collective/preventactions/profiles/default/metadata.xml
collective/preventactions/profiles/testing/metadata.xml
collective/preventactions/profiles/testing/properties.xml
collective/preventactions/profiles/uninstall/actions.xml
collective/preventactions/profiles/uninstall/browserlayer.xml
collective/preventactions/tests/__init__.py
collective/preventactions/tests/example.robot
collective/preventactions/tests/test_actions.py
collective/preventactions/tests/test_form.py
collective/preventactions/tests/test_install.py
collective/preventactions/tests/test_robot.py
collective/preventactions/tests/test_views.py
collective.preventactions-0.2.1.dist-info/DESCRIPTION.rst
collective.preventactions-0.2.1.dist-info/METADATA
collective.preventactions-0.2.1.dist-info/RECORD
collective.preventactions-0.2.1.dist-info/WHEEL
collective.preventactions-0.2.1.dist-info/entry_points.txt
collective.preventactions-0.2.1.dist-info/metadata.json
collective.preventactions-0.2.1.dist-info/namespace_packages.txt
collective.preventactions-0.2.1.dist-info/top_level.txt
