Metadata-Version: 2.0
Name: collective.preventactions
Version: 0.2.1
Summary: This package allows administrateur to marker object which can't be deleted
Home-page: http://pypi.python.org/pypi/collective.preventactions
Author: Benoît Suttor
Author-email: benoit.suttor@imio.be
License: BSD
Keywords: Plone Python Zope
Platform: UNKNOWN
Classifier: Framework :: Plone
Classifier: Programming Language :: Python
Provides-Extra: test
Requires-Dist: Plone
Requires-Dist: Products.GenericSetup (>=1.8.2)
Requires-Dist: setuptools
Requires-Dist: plone.api
Provides-Extra: test
Requires-Dist: plone.app.robotframework; extra == 'test'
